hypermodel/__init__.py
hypermodel/cli/__init__.py
hypermodel/cli/cli_start.py
hypermodel/cli/groups/__init__.py
hypermodel/cli/groups/k8s.py
hypermodel/cli/groups/lake.py
hypermodel/cli/groups/warehouse.py
hypermodel/features/__init__.py
hypermodel/features/categorical.py
hypermodel/features/numerical.py
hypermodel/hml/__init__.py
hypermodel/hml/_inference_deployment.py
hypermodel/hml/decorators.py
hypermodel/hml/hml_app.py
hypermodel/hml/hml_container_op.py
hypermodel/hml/hml_global.py
hypermodel/hml/hml_inference_app.py
hypermodel/hml/hml_inference_deployment.py
hypermodel/hml/hml_package.py
hypermodel/hml/hml_pipeline.py
hypermodel/hml/hml_pipeline_app.py
hypermodel/hml/prediction/__init__.py
hypermodel/kubeflow/__init__.py
hypermodel/kubeflow/deploy.py
hypermodel/kubeflow/deploy_dev.py
hypermodel/kubeflow/kubeflow_client.py
hypermodel/model/__init__.py
hypermodel/model/table_schema.py
hypermodel/platform/__init__.py
hypermodel/platform/gcp/__init__.py
hypermodel/platform/gcp/config.py
hypermodel/platform/gcp/data_lake.py
hypermodel/platform/gcp/data_warehouse.py
hypermodel/platform/gcp/gcp_base_op.py
hypermodel/platform/gcp/services.py
hypermodel/platform/local/__init__.py
hypermodel/platform/local/config.py
hypermodel/platform/local/data_lake.py
hypermodel/platform/local/data_warehouse.py
hypermodel/platform/local/services.py
hypermodel/utilities/__init__.py
hypermodel/utilities/file_hash.py
hypermodel/utilities/hm_shell.py
hypermodel/utilities/k8s.py
hypermodel/utilities/kubeflow.py
hypermodel-0.1.80.dist-info/LICENSE
hypermodel-0.1.80.dist-info/METADATA
hypermodel-0.1.80.dist-info/WHEEL
hypermodel-0.1.80.dist-info/entry_points.txt
hypermodel-0.1.80.dist-info/top_level.txt
hypermodel-0.1.80.dist-info/RECORD
