Metadata-Version: 2.1
Name: hypermodel
Version: 0.1.80
Summary: Hyper Model provides functionality to support MLOps
Home-page: UNKNOWN
Author: Growing Data
License: UNKNOWN
Platform: UNKNOWN
Classifier: Intended Audience :: Developers
Classifier: Intended Audience :: Education
Classifier: Intended Audience :: Science/Research
Classifier: License :: OSI Approved :: Apache Software License
Classifier: Programming Language :: Python :: 3
Classifier: Programming Language :: Python :: 3.5
Classifier: Programming Language :: Python :: 3.6
Classifier: Programming Language :: Python :: 3.7
Classifier: Topic :: Scientific/Engineering
Classifier: Topic :: Scientific/Engineering :: Artificial Intelligence
Classifier: Topic :: Software Development
Classifier: Topic :: Software Development :: Libraries
Classifier: Topic :: Software Development :: Libraries :: Python Modules
Requires-Python: >=3.5.3
Requires-Dist: click
Requires-Dist: kfp
Requires-Dist: pandas
Requires-Dist: joblib
Requires-Dist: google-cloud
Requires-Dist: google-cloud-bigquery
Requires-Dist: tqdm
Requires-Dist: python-gitlab
Requires-Dist: flask
Requires-Dist: waitress
Requires-Dist: sphinx-rtd-theme
Requires-Dist: kubernetes (<=9.0.0,>=8.0.0)
